l1000geom/__init__.py
legend_pygeom_l1000-0.3.0.dist-info/licenses/LICENSE
pygeoml1000/__init__.py
pygeoml1000/_version.py
pygeoml1000/cavern_and_labs.py
pygeoml1000/cli.py
pygeoml1000/core.py
pygeoml1000/cryo.py
pygeoml1000/dummy_metadata_generator.py
pygeoml1000/fibers.py
pygeoml1000/hpge_strings.py
pygeoml1000/rt_profiles.py
pygeoml1000/watertank.py
pygeoml1000/watertank_instrumentation.py
pygeoml1000/wlsr.py
pygeoml1000/configs/config.json
pygeoml1000/materials/__init__.py
pygeoml1000/materials/ketek_sipm.py
pygeoml1000/materials/surfaces.py
pygeoml1000/models/BasePlate_large.stl
pygeoml1000/models/BasePlate_medium.stl
pygeoml1000/models/BasePlate_medium_ortec.stl
pygeoml1000/models/BasePlate_small.stl
pygeoml1000/models/BasePlate_xlarge.stl
pygeoml1000/models/README.md
pygeoml1000/models/StringSupportStructure.stl
pygeoml1000/models/TopPlate.stl
pygeoml1000/models/TopPlate_ppc.stl
pygeoml1000/models/TriStar_large.stl
pygeoml1000/models/TriStar_medium.stl
pygeoml1000/models/TriStar_small.stl
pygeoml1000/models/TriStar_xlarge.stl
legend_pygeom_l1000-0.3.0.dist-info/METADATA
legend_pygeom_l1000-0.3.0.dist-info/WHEEL
legend_pygeom_l1000-0.3.0.dist-info/entry_points.txt
legend_pygeom_l1000-0.3.0.dist-info/top_level.txt
legend_pygeom_l1000-0.3.0.dist-info/RECORD
