Metadata-Version: 2.4
Name: legend_pygeom_l1000
Version: 0.3.0
Summary: Geometry model of the LEGEND-1000 experimental setup
Author-email: Moritz Neuberger <moritz.neuberger@tum.de>
Maintainer: The LEGEND Collaboration
License-Expression: GPL-3.0
Project-URL: Homepage, https://github.com/legend-exp/legend-pygeom-l1000
Project-URL: Bug Tracker, https://github.com/legend-exp/legend-pygeom-l1000/issues
Project-URL: Discussions, https://github.com/legend-exp/legend-pygeom-l1000/discussions
Project-URL: Changelog, https://github.com/legend-exp/legend-pygeom-l1000/releases
Classifier: Intended Audience :: Developers
Classifier: Intended Audience :: Science/Research
Classifier: Operating System :: MacOS
Classifier: Operating System :: POSIX
Classifier: Operating System :: Unix
Classifier: Programming Language :: Python
Classifier: Programming Language :: Python :: 3
Classifier: Programming Language :: Python :: 3 :: Only
Classifier: Topic :: Scientific/Engineering
Requires-Python: >=3.10
License-File: LICENSE
Requires-Dist: legend-pygeom-hpges>=0.9.0
Requires-Dist: legend-pygeom-optics>=0.15
Requires-Dist: legend-pygeom-tools>=0.0.25
Requires-Dist: numpy
Requires-Dist: pint
Requires-Dist: pyg4ometry
Requires-Dist: dbetto
Requires-Dist: pylegendmeta>=1.3.1
Requires-Dist: pyyaml
Requires-Dist: scipy
Provides-Extra: all
Requires-Dist: legend-pygeom-l1000[docs,test]; extra == "all"
Provides-Extra: docs
Requires-Dist: furo; extra == "docs"
Requires-Dist: myst-parser; extra == "docs"
Requires-Dist: sphinx; extra == "docs"
Requires-Dist: sphinx-copybutton; extra == "docs"
Requires-Dist: sphinx-subfigure; extra == "docs"
Provides-Extra: test
Requires-Dist: pre-commit; extra == "test"
Requires-Dist: pylegendtestdata; extra == "test"
Requires-Dist: pytest>=6.0; extra == "test"
Requires-Dist: pytest-cov; extra == "test"
Dynamic: license-file
